files_7/dmactr.v
`include "define.h"
module dmactr (output reg [`BUS_ADDR_WIDTH-1:0] addr, // メモリ・I/Oアドレス
               output reg [`DATA_WIDTH-1:0] odata,    // 書き込みデータ
               input [`DATA_WIDTH-1:0] idata,         // 読み込みデータ
               output reg rw_,                        // リードライト信号
               output reg breq_,                      // バス要求
               input bgrt_,                           // バス許可
               input [`BUS_ADDR_WIDTH-1:0] dsaddr,    // DMA転送元アドレス
               input [`BUS_ADDR_WIDTH-1:0] ddaddr,    // DMA転送先アドレス
               input [1:0] dmode,                     // DMA転送モード
               input dreq_,                           // I/O側が生成する場合も
               output reg eop_,                       // DMA転送完了
               input reset_,
               input clk);

reg [2:0] state;

always @ (posedge clk)
    if (reset_ == `Enable_) begin
        // stateの初期化を怠るとちゃんと動かないので注意！
        state <= `Wait;
        breq_ <= `Disable_;
        end else begin
        case (state)
            `Wait:
            begin
                if (dreq_ == `Enable_) begin
                    breq_ <= `Enable_;
                    state <= `Read1;
                end
                eop_ <= `Disable_;
            end
            `Read1:
            if (bgrt_ == `Enable_) begin
                addr <= dsaddr;
                rw_ <= `Read;
                state <= `Write1;
            end
            `Write1:
            begin
                addr <= ddaddr;
                rw_ <= `Write;
                odata <= idata;
                state <= `Complete;
            end
            `Complete:
            begin
                eop_ <= `Enable_;
                breq_ <= `Disable_;
                state <= `Wait;
            end
        endcase
    end
endmodule

files_7/busarb.v
`include "define.h"
module busarb (input breq0_,
               input breq1_,
               output bgrt0_,
               output bgrt1_,
               input reset_,
               input clk);
    reg state;
    assign bgrt0_ = (state == `BGRT0) ? `Enable_ : `Disable_;
    assign bgrt1_ = (state == `BGRT1) ? `Enable_ : `Disable_;
    always @ (posedge clk)
        if (reset_ == `Enable_) begin
            // stateの初期化を怠るとちゃんと動かないので注意！
            // 不定値が入らなければ良い
            state <= `BGRT0;
            end else begin
            case (state)
                `BGRT0: if (breq0_ == `Disable_ && breq1_ == `Enable_)
                state <= `BGRT1;
                `BGRT1: if (breq1_ == `Disable_ && breq0_ == `Enable_)
                state <= `BGRT0;
            endcase
        end
endmodule

files_7/timer.v
`include "define.h"
module timer (input [`MEM_ADDR_WIDTH-1:0] addr,
              input [`DATA_WIDTH-1:0] idata,
              output [`DATA_WIDTH-1:0] odata,
              input cs_,
              input rw_,
              input clk,
              input rst_);

reg [31:0] count;
reg en;
wire clear, start, stop;

assign clear = (cs_ == `Enable_ && rw_ == `Write && addr == 4 && idata == 1);
assign start = (cs_ == `Enable_ && rw_ == `Write && addr == 4 && idata == 2);
assign stop  = (cs_ == `Enable_ && rw_ == `Write && addr == 4 && idata == 4);

// 一つのregは一箇所のalwaysで実行、二重書きがなくなる
always @ (posedge clk)
    if (rst_ == `Enable_)
        count <= 0;
    else if (clear)
        count <= 0;
    else if (en)
        count <= count + 1;


always @ (posedge clk)
    if (rst_ == `Enable_)
        en <= 0;
    else if (start)
        en <= `Enable;
    else if (stop)
        en <= `Disable;

assign odata = 
(addr == 0) ? count[7:0] :
(addr == 1) ? count [15:8] :
(addr == 2) ? count [23:16] :
(addr == 3) ? count [31:24] : 0;
endmodule

files_7/sram.v
`include "define.h"

module sram (input [`MEM_ADDR_WIDTH-1:0] addr,
             input [`DATA_WIDTH-1:0] idata,
             output [`DATA_WIDTH-1:0] odata,
             input cs_,
             input rw_,
             input clk);

reg [`DATA_WIDTH-1:0] mem [(1<<`MEM_ADDR_WIDTH)-1:0];

assign odata = mem[addr];

always @ (posedge clk)
    if (cs_ == `Enable_ && rw_ == `Write)
        mem[addr] <= idata;

endmodule

files_7/addrdec.v
`include "define.h"
module addrdec (input [`BUS_ADDR_WIDTH-1:0] addr,
                output cs0_,
                output cs1_,
                output cs2_,
                output cs3_);
assign  cs0_ = (~addr[8] & ~addr[9]) ? `Enable_ : `Disable_;
assign  cs1_ = (addr[8] & ~addr[9]) ? `Enable_ : `Disable_;
assign  cs2_ = (~addr[8] & addr[9]) ? `Enable_ : `Disable_;
assign  cs3_ = (addr[8] & addr[9]) ? `Enable_ : `Disable_;
endmodule

files_7/slaves.v
`include "define.h"
module slaves (input [`BUS_ADDR_WIDTH-1:0] addr,
               input [`DATA_WIDTH-1:0] idata,
               output [`DATA_WIDTH-1:0] odata,
               input rw_,
               input reset_,
               input clk);

wire [`DATA_WIDTH-1:0] odata0, odata1, odata2;
wire cs0_, cs1_, cs2_, cs3_;

addrdec addrdec(addr, cs0_, cs1_, cs2_, cs3_);

// 下位8bitのaddr
sram u0(addr[`MEM_ADDR_WIDTH-1:0], idata, odata0, cs0_, rw_, clk);
sram u1(addr[`MEM_ADDR_WIDTH-1:0], idata, odata1, cs1_, rw_, clk);
timer timer(addr[`MEM_ADDR_WIDTH-1:0], idata, odata2, cs2_, rw_, clk, reset_);

assign odata = (cs0_ == `Enable_) ? odata0 : (cs1_ == `Enable_) ? odata1 : (cs2_ == `Enable_) ? odata2 : 0;

endmodule

files_7/top.v
module top (input [`BUS_ADDR_WIDTH-1:0] addr0,
            input [`DATA_WIDTH-1:0] idata0,
            output [`DATA_WIDTH-1:0] odata0,
            input rw0_,
            input breq0_,
            output bgrt0_,
            input [`BUS_ADDR_WIDTH-1:0] dsaddr, // DMA転送元アドレス
            input [`BUS_ADDR_WIDTH-1:0] ddaddr, // DMA転送先アドレス
            input [1:0] dmode,                  // DMA転送モード
            input dreq_,                        // I/O側が生成する場合も
            output eop_,                        // DMA転送完了
            input reset_,
            input clk);

wire [`DATA_WIDTH-1:0] odata, idata;
wire [`BUS_ADDR_WIDTH-1:0] addr;
wire rw_;

// マスタデバイス１（DMAコントローラ）
wire [`BUS_ADDR_WIDTH-1:0] addr1;
wire [`DATA_WIDTH-1:0] idata1;
wire [`DATA_WIDTH-1:0] odata1;
wire rw1_, breq1_, bgrt1_;

assign odata0 = odata;
assign odata1 = odata;

assign addr  = (bgrt0_ == `Enable_) ? addr0 : addr1;   // addr0もしくはaddr1（bgrtをもらった方）
assign idata = (bgrt0_ == `Enable_) ? idata0 : idata1; // idata0もしくはidata1（bgrtをもらった方）
assign rw_   = (bgrt0_ == `Enable_) ? rw0_ : rw1_;     // rw0_もしくはrw1_（bgrtをもらった方）
slaves u0 (addr, idata, odata, rw_, reset_, clk);
busarb u1 (breq0_, breq1_, bgrt0_, bgrt1_, reset_, clk);
dmactr u2 (addr1, idata1, odata1, rw1_, breq1_, bgrt1_, dsaddr, ddaddr, dmode, dreq_, eop_, reset_, clk);

endmodule

files_7/test_dma.v
`timescale 1ns/10ps
`include "define.h"
module test ();
    
    reg [`BUS_ADDR_WIDTH-1:0] addr;
    reg [`DATA_WIDTH-1:0] idata;
    wire [`DATA_WIDTH-1:0] odata;
    reg rw_, breq_;
    wire bgrt_, eop_;
    reg dreq_;
    reg clk, reset_;
    reg [`BUS_ADDR_WIDTH-1:0] dsaddr, ddaddr;
    reg [1:0] dmode;
    
    top u0 (addr, idata, odata, rw_, breq_, bgrt_, dsaddr, ddaddr, dmode, dreq_, eop_, reset_, clk);
    
    always begin
        clk <= 1; #1; clk <= 0; #1;
    end
    
    initial begin
        #1;
        $dumpfile("dump.vcd");
        $dumpvars(0, test.u0);
        
        reset_ <= `Enable_;
        #2;
        reset_ <= `Disable_;
        dreq_ <= `Disable_;
        breq_ <= `Enable_;
        #2;
        
        // プロセッサによる処理
        rw_ <= `Write;
        addr <= 10'h150;
        idata <= 8'h99;
        
        #2;
        
        rw_ <= `Read;
        addr <= 10'h150;
        idata <= 0; #10;
        
        
        // odata取れた
        $display("addr = %h odata = %h", addr, odata);
        
        // DMAによる処理
        
        // DMA転送 Memory-to-Memory
        #10;
        breq_ <= `Disable_;
        dreq_ <= `Enable_;
        dmode <= `BurstM2M;
        dsaddr <= 10'h150;
        ddaddr <= 10'h160;
        
        #2;
        dreq_ <= `Disable_;
        #20;
        // 読み取り
        breq_ <= `Enable_;
        rw_ <= `Read;
        addr <= 10'h160;
        
        #12;
        $display("addr = %h odata = %h", addr, odata);
        
        $finish;
        
    end
endmodule

files_7/dump.vcd
$date
	Sat May 22 02:43:24 2021
$end
$version
	Icarus Verilog
$end
$timescale
	10ps
$end
$scope module test $end
$scope module u0 $end
$var wire 10 ! addr0 [9:0] $end
$var wire 1 " breq0_ $end
$var wire 1 # clk $end
$var wire 10 $ ddaddr [9:0] $end
$var wire 2 % dmode [1:0] $end
$var wire 1 & dreq_ $end
$var wire 10 ' dsaddr [9:0] $end
$var wire 8 ( idata0 [7:0] $end
$var wire 8 ) odata0 [7:0] $end
$var wire 8 * odata1 [7:0] $end
$var wire 1 + reset_ $end
$var wire 1 , rw0_ $end
$var wire 1 - rw_ $end
$var wire 1 . rw1_ $end
$var wire 8 / odata [7:0] $end
$var wire 8 0 idata1 [7:0] $end
$var wire 8 1 idata [7:0] $end
$var wire 1 2 eop_ $end
$var wire 1 3 breq1_ $end
$var wire 1 4 bgrt1_ $end
$var wire 1 5 bgrt0_ $end
$var wire 10 6 addr1 [9:0] $end
$var wire 10 7 addr [9:0] $end
$scope module u0 $end
$var wire 10 8 addr [9:0] $end
$var wire 1 # clk $end
$var wire 8 9 idata [7:0] $end
$var wire 1 + reset_ $end
$var wire 1 - rw_ $end
$var wire 8 : odata2 [7:0] $end
$var wire 8 ; odata1 [7:0] $end
$var wire 8 < odata0 [7:0] $end
$var wire 8 = odata [7:0] $end
$var wire 1 > cs3_ $end
$var wire 1 ? cs2_ $end
$var wire 1 @ cs1_ $end
$var wire 1 A cs0_ $end
$scope module addrdec $end
$var wire 10 B addr [9:0] $end
$var wire 1 > cs3_ $end
$var wire 1 ? cs2_ $end
$var wire 1 @ cs1_ $end
$var wire 1 A cs0_ $end
$upscope $end
$scope module timer $end
$var wire 8 C addr [7:0] $end
$var wire 1 D clear $end
$var wire 1 # clk $end
$var wire 1 ? cs_ $end
$var wire 8 E idata [7:0] $end
$var wire 1 + rst_ $end
$var wire 1 - rw_ $end
$var wire 1 F start $end
$var wire 1 G stop $end
$var wire 8 H odata [7:0] $end
$var reg 32 I count [31:0] $end
$var reg 1 J en $end
$upscope $end
$scope module u0 $end
$var wire 8 K addr [7:0] $end
$var wire 1 # clk $end
$var wire 1 A cs_ $end
$var wire 8 L idata [7:0] $end
$var wire 8 M odata [7:0] $end
$var wire 1 - rw_ $end
$upscope $end
$scope module u1 $end
$var wire 8 N addr [7:0] $end
$var wire 1 # clk $end
$var wire 1 @ cs_ $end
$var wire 8 O idata [7:0] $end
$var wire 8 P odata [7:0] $end
$var wire 1 - rw_ $end
$upscope $end
$upscope $end
$scope module u1 $end
$var wire 1 " breq0_ $end
$var wire 1 # clk $end
$var wire 1 + reset_ $end
$var wire 1 3 breq1_ $end
$var wire 1 4 bgrt1_ $end
$var wire 1 5 bgrt0_ $end
$var reg 1 Q state $end
$upscope $end
$scope module u2 $end
$var wire 1 4 bgrt_ $end
$var wire 1 # clk $end
$var wire 10 R ddaddr [9:0] $end
$var wire 2 S dmode [1:0] $end
$var wire 1 & dreq_ $end
$var wire 10 T dsaddr [9:0] $end
$var wire 8 U idata [7:0] $end
$var wire 1 + reset_ $end
$var reg 10 V addr [9:0] $end
$var reg 1 3 breq_ $end
$var reg 1 2 eop_ $end
$var reg 8 W odata [7:0] $end
$var reg 1 . rw_ $end
$var reg 3 X state [2:0] $end
$upscope $end
$upscope $end
$upscope $end
$enddefinitions $end
#100
$dumpvars
bx X
bx W
bx V
bx U
bx T
bx S
bx R
xQ
bx P
bx O
bx N
bx M
bx L
bx K
xJ
bx I
bx H
xG
xF
bx E
xD
bx C
bx B
xA
x@
x?
x>
bx =
bx <
bx ;
bx :
bx 9
bx 8
bx 7
bx 6
x5
x4
x3
x2
bx 1
bx 0
bx /
x.
x-
x,
0+
bx *
bx )
bx (
bx '
x&
bx %
bx $
0#
x"
bx !
$end
#200
05
14
b0 :
b0 H
13
b0 X
0Q
0J
b0 I
1#
#300
0#
0"
1&
1+
#400
12
1#
#500
1A
0@
1?
1>
0D
0F
0G
b1010000 K
b1010000 N
b1010000 C
b10011001 1
b10011001 9
b10011001 E
b10011001 L
b10011001 O
b101010000 7
b101010000 8
b101010000 B
0-
0#
b10011001 (
b101010000 !
0,
#600
b10011001 *
b10011001 U
b10011001 )
b10011001 /
b10011001 =
b10011001 ;
b10011001 P
1#
#700
b0 1
b0 9
b0 E
b0 L
b0 O
1-
0#
b0 (
1,
#800
1#
#900
0#
#1000
1#
#1100
0#
#1200
1#
#1300
0#
#1400
1#
#1500
0#
#1600
1#
#1700
0#
#1800
1#
#1900
0#
#2000
1#
#2100
0#
#2200
1#
#2300
0#
#2400
1#
#2500
0#
#2600
1#
#2700
0#
b101100000 $
b101100000 R
b101010000 '
b101010000 T
b1 %
b1 S
0&
1"
#2800
b1 X
03
1#
#2900
0#
1&
#3000
xD
xF
xG
xA
x?
x@
x>
bx *
bx U
bx )
bx /
bx =
bx K
bx ;
bx P
bx N
bx C
x-
bx 1
bx 9
bx E
bx L
bx O
bx 7
bx 8
bx B
15
04
1Q
1#
#3100
0#
#3200
b10011001 *
b10011001 U
b10011001 )
b10011001 /
b10011001 =
1A
0@
1?
1>
0D
0F
0G
b1010000 K
b10011001 ;
b10011001 P
b1010000 N
b1010000 C
1-
b101010000 7
b101010000 8
b101010000 B
b10 X
1.
b101010000 6
b101010000 V
1#
#3300
0#
#3400
bx *
bx U
bx )
bx /
bx =
b1100000 K
bx ;
bx P
b1100000 N
b1100000 C
b10011001 1
b10011001 9
b10011001 E
b10011001 L
b10011001 O
0-
b101100000 7
b101100000 8
b101100000 B
b11 X
b10011001 0
b10011001 W
0.
b101100000 6
b101100000 V
1#
#3500
0#
#3600
b10011001 *
b10011001 U
b10011001 )
b10011001 /
b10011001 =
b10011001 ;
b10011001 P
b0 X
13
02
1#
#3700
0#
#3800
12
1#
#3900
0#
#4000
1#
#4100
0#
#4200
1#
#4300
0#
#4400
1#
#4500
0#
#4600
1#
#4700
0#
#4800
1#
#4900
0#
b101100000 !
0"
#5000
1-
b0 1
b0 9
b0 E
b0 L
b0 O
05
14
0Q
1#
